{
    "tanish": {
     "username": "tanish",
     "name": "Tanish",
     "encryptedPassword": "$2b$10$guiNjhR0cW6ce5BSSxVGeuYPrB6gxxgMMfe1b4v6ScqbmgydcIxnu"
    },
    "sheep": {
     "username": "sheep",
     "name": "Sheep",
     "encryptedPassword": "$2b$10$e/EE3sVmj3sgw02Uy.mM8.auhn/ZSv0DziWHZyFOin6lsUKeT3cJ6"
    },
    "roblox": {
     "username": "roblox",
     "name": "robo",
     "encryptedPassword": "$2b$10$vX6IFVvCZ.ZlKdluupKnduWPz5iAkyRDrzcyOU5VA12zchnEZjbj."
    },
    "lorax": {
     "username": "lorax",
     "name": "lorax",
     "encryptedPassword": "$2b$10$emLY6kDt2cJRhQClwbepBuAGYM7K0OvxuxqSEqGsJvrxgTtA7aaDG"
    },
    "del": {
     "username": "del",
     "name": "del",
     "encryptedPassword": "$2b$10$5dn8ehjxiKYmYFk8XiZBLuQ/6tr3fM98D7OJsejBstsRWs5B8cSvm"
    },
    "del2": {
     "username": "del2",
     "name": "del2",
     "encryptedPassword": "$2b$10$NixTgLGbZXeQNjjkpOtcvu770E.fG0xXbWxgdgPUkKhp4jZXGBWgK"
    },
    "yas": {
     "username": "yas",
     "name": "yas",
     "encryptedPassword": "$2b$10$mmZJquuO3IU60isVmlkvGemzoWHtvsLM4xAXAI2V7SsjKq704raPa"
    },
    "poo": {
     "username": "poo",
     "name": "poo",
     "encryptedPassword": "$2b$10$JZHhVrI8siLlHhT09Mgy8epg3Lu0YL6QQ3StcaoB33mYPbnoIvvDS"
    },
    "Rishab": {
     "username": "Rishab",
     "name": "Rishab",
     "encryptedPassword": "$2b$10$X86nOy.1DgdSkaLOR/9Dq.fPmoXjtJDL5LlRs.3XC3PO7/SgWFV06"
    },
    "Table": {
     "username": "Table",
     "name": "Table",
     "encryptedPassword": "$2b$10$TFaxyAU1ACnUQaCLLWoUKeLItSbIT5.xDcTE9hAYeTXYayc7e50/S"
    }
   }